{"base": "EUR", "last_updated": "2022-12-06 08:00:45", "ARS": {"from": "EUR", "to": "ARS", "rate": "177.46"}, "BOB": {"from": "EUR", "to": "BOB", "rate": "7.29"}, "BRL": {"from": "EUR", "to": "BRL", "rate": "5.54"}, "CLP": {"from": "EUR", "to": "CLP", "rate": "940.10"}, "COP": {"from": "EUR", "to": "COP", "rate": "5061.89"}, "CRC": {"from": "EUR", "to": "CRC", "rate": "635.76"}, "CUP": {"from": "EUR", "to": "CUP", "rate": "25.31"}, "DOP": {"from": "EUR", "to": "DOP", "rate": "57.61"}, "USD": {"from": "EUR", "to": "USD", "rate": "1.05"}, "SVC": {"from": "EUR", "to": "SVC", "rate": "9.23"}, "GTQ": {"from": "EUR", "to": "GTQ", "rate": "8.29"}, "HNL": {"from": "EUR", "to": "HNL", "rate": "26.03"}, "MXN": {"from": "EUR", "to": "MXN", "rate": "20.68"}, "NIO": {"from": "EUR", "to": "NIO", "rate": "38.50"}, "PAB": {"from": "EUR", "to": "PAB", "rate": "1.05"}, "PYG": {"from": "EUR", "to": "PYG", "rate": "7588.39"}, "PEN": {"from": "EUR", "to": "PEN", "rate": "4.05"}, "UYU": {"from": "EUR", "to": "UYU", "rate": "41.21"}, "VEF": {"from": "EUR", "to": "VEF", "rate": 0}}