{
    "ARS": {
        "sourceCurrency": "EUR",
        "targetCurrency": "ARS",
        "sourceCountry": null,
        "targetCountry": null,
        "providerCountry": null,
        "providerType": null,
        "sendAmount": 100.0,
        "providers": [
            {
                "id": 46,
                "alias": "n26",
                "name": "N26",
                "logo": "https://dq8dwmysp7hk1.cloudfront.net/logos/N26.svg",
                "logos": {
                    "normal": {
                        "svgUrl": "https://dq8dwmysp7hk1.cloudfront.net/logos/N26.svg",
                        "pngUrl": "https://dq8dwmysp7hk1.cloudfront.net/logos/N26.png"
                    },
                    "inverse": {
                        "svgUrl": null,
                        "pngUrl": null
                    },
                    "white": {
                        "svgUrl": "https://dq8dwmysp7hk1.cloudfront.net/logos/N26--white.svg",
                        "pngUrl": "https://dq8dwmysp7hk1.cloudfront.net/logos/N26--white.png"
                    }
                },
                "type": "bank",
                "partner": true,
                "quotes": [
                    {
                        "rate": 200.755,
                        "fee": 4.26,
                        "receivedAmount": 19220.28,
                        "dateCollected": "2023-01-24T08:01:10Z",
                        "sourceCountry": null,
                        "targetCountry": null,
                        "markup": 0.0,
                        "deliveryEstimation": {
                            "duration": {
                                "min": "PT6H28M49.652799596S",
                                "max": "PT6H28M49.652799596S"
                            },
                            "providerGivesEstimate": true
                        }
                    }
                ]
            },
            {
                "id": 39,
                "alias": "wise",
                "name": "Wise",
                "logo": "https://wise.com/public-resources/assets/logos/wise/brand_logo.svg",
                "logos": {
                    "normal": {
                        "svgUrl": "https://wise.com/public-resources/assets/logos/wise/brand_logo.svg",
                        "pngUrl": "https://wise.com/public-resources/assets/logos/wise/brand_logo.png"
                    },
                    "inverse": {
                        "svgUrl": "https://wise.com/public-resources/assets/logos/wise/brand_logo_inverse.svg",
                        "pngUrl": "https://wise.com/public-resources/assets/logos/wise/brand_logo_inverse.png"
                    },
                    "white": {
                        "svgUrl": "https://wise.com/public-resources/assets/logos/wise/brand_logo_white.svg",
                        "pngUrl": "https://wise.com/public-resources/assets/logos/wise/brand_logo_white.png"
                    }
                },
                "type": "moneyTransferProvider",
                "partner": false,
                "quotes": [
                    {
                        "rate": 200.755,
                        "fee": 4.26,
                        "receivedAmount": 19220.28,
                        "dateCollected": "2023-01-24T08:01:10Z",
                        "sourceCountry": null,
                        "targetCountry": null,
                        "markup": 0.0,
                        "deliveryEstimation": {
                            "duration": {
                                "min": "PT6H28M49.64998556S",
                                "max": "PT6H28M49.64998556S"
                            },
                            "providerGivesEstimate": true
                        }
                    }
                ]
            }
        ]
    },
    "BOB": {
        "sourceCurrency": "EUR",
        "targetCurrency": "BOB",
        "sourceCountry": null,
        "targetCountry": null,
        "providerCountry": null,
        "providerType": null,
        "sendAmount": 100.0,
        "providers": []
    },
    "BRL": {
        "sourceCurrency": "EUR",
        "targetCurrency": "BRL",
        "sourceCountry": null,
        "targetCountry": null,
        "providerCountry": null,
        "providerType": null,
        "sendAmount": 100.0,
        "providers": [
            {
                "id": 78,
                "alias": "activobank",
                "name": "ActivoBank",
                "logo": "https://dq8dwmysp7hk1.cloudfront.net/logos/activo.svg",
                "logos": {
                    "normal": {
                        "svgUrl": "https://dq8dwmysp7hk1.cloudfront.net/logos/activo.svg",
                        "pngUrl": "https://dq8dwmysp7hk1.cloudfront.net/logos/activo.png"
                    },
                    "inverse": {
                        "svgUrl": null,
                        "pngUrl": null
                    },
                    "white": {
                        "svgUrl": "https://dq8dwmysp7hk1.cloudfront.net/logos/activo--white.svg",
                        "pngUrl": "https://dq8dwmysp7hk1.cloudfront.net/logos/activo--white.png"
                    }
                },
                "type": "bank",
                "partner": true,
                "quotes": [
                    {
                        "rate": 5.67,
                        "fee": 1.78,
                        "receivedAmount": 556.91,
                        "dateCollected": "2023-01-24T07:57:26Z",
                        "sourceCountry": null,
                        "targetCountry": null,
                        "markup": 0.0,
                        "deliveryEstimation": {
                            "duration": {
                                "min": "PT9H1M55.354458565S",
                                "max": "PT9H1M55.354458565S"
                            },
                            "providerGivesEstimate": true
                        }
                    }
                ]
            },
            {
                "id": 104,
                "alias": "remitly",
                "name": "Remitly",
                "logo": "https://dq8dwmysp7hk1.cloudfront.net/logos/remitly.svg",
                "logos": {
                    "normal": {
                        "svgUrl": "https://dq8dwmysp7hk1.cloudfront.net/logos/remitly.svg",
                        "pngUrl": "https://dq8dwmysp7hk1.cloudfront.net/logos/remitly.png"
                    },
                    "inverse": {
                        "svgUrl": null,
                        "pngUrl": null
                    },
                    "white": {
                        "svgUrl": "https://dq8dwmysp7hk1.cloudfront.net/logos/remitly--white.svg",
                        "pngUrl": "https://dq8dwmysp7hk1.cloudfront.net/logos/remitly--white.png"
                    }
                },
                "type": "moneyTransferProvider",
                "partner": false,
                "quotes": [
                    {
                        "rate": 5.57589939,
                        "fee": 1.99,
                        "receivedAmount": 546.49,
                        "dateCollected": "2023-01-24T07:43:34.470269Z",
                        "sourceCountry": "DE",
                        "targetCountry": "BR",
                        "markup": 1.66413198,
                        "deliveryEstimation": {
                            "duration": null,
                            "providerGivesEstimate": true
                        }
                    }
                ]
            },
            {
                "id": 43,
                "alias": "ing-nl",
                "name": "ING",
                "logo": "https://dq8dwmysp7hk1.cloudfront.net/logos/ingnl.svg",
                "logos": {
                    "normal": {
                        "svgUrl": "https://dq8dwmysp7hk1.cloudfront.net/logos/ingnl.svg",
                        "pngUrl": "https://dq8dwmysp7hk1.cloudfront.net/logos/ingnl.png"
                    },
                    "inverse": {
                        "svgUrl": null,
                        "pngUrl": null
                    },
                    "white": {
                        "svgUrl": "https://dq8dwmysp7hk1.cloudfront.net/logos/ingnl--white.svg",
                        "pngUrl": "https://dq8dwmysp7hk1.cloudfront.net/logos/ingnl--white.png"
                    }
                },
                "type": "bank",
                "partner": false,
                "quotes": [
                    {
                        "rate": 5.67026,
                        "fee": 31.0,
                        "receivedAmount": 391.25,
                        "dateCollected": "2023-01-24T07:20:01.038613Z",
                        "sourceCountry": "NL",
                        "targetCountry": "BR",
                        "markup": 0.0,
                        "deliveryEstimation": {
                            "duration": null,
                            "providerGivesEstimate": true
                        }
                    }
                ]
            },
            {
                "id": 45,
                "alias": "bunq",
                "name": "bunq",
                "logo": "https://dq8dwmysp7hk1.cloudfront.net/logos/bunq.svg",
                "logos": {
                    "normal": {
                        "svgUrl": "https://dq8dwmysp7hk1.cloudfront.net/logos/bunq.svg",
                        "pngUrl": "https://dq8dwmysp7hk1.cloudfront.net/logos/bunq.png"
                    },
                    "inverse": {
                        "svgUrl": null,
                        "pngUrl": null
                    },
                    "white": {
                        "svgUrl": "https://dq8dwmysp7hk1.cloudfront.net/logos/bunq--white.svg",
                        "pngUrl": "https://dq8dwmysp7hk1.cloudfront.net/logos/bunq--white.png"
                    }
                },
                "type": "bank",
                "partner": true,
                "quotes": [
                    {
                        "rate": 5.67,
                        "fee": 1.78,
                        "receivedAmount": 556.91,
                        "dateCollected": "2023-01-24T07:57:26Z",
                        "sourceCountry": null,
                        "targetCountry": null,
                        "markup": 0.0,
                        "deliveryEstimation": {
                            "duration": {
                                "min": "PT9H1M55.354354507S",
                                "max": "PT9H1M55.354354507S"
                            },
                            "providerGivesEstimate": true
                        }
                    }
                ]
            },
            {
                "id": 39,
                "alias": "wise",
                "name": "Wise",
                "logo": "https://wise.com/public-resources/assets/logos/wise/brand_logo.svg",
                "logos": {
                    "normal": {
                        "svgUrl": "https://wise.com/public-resources/assets/logos/wise/brand_logo.svg",
                        "pngUrl": "https://wise.com/public-resources/assets/logos/wise/brand_logo.png"
                    },
                    "inverse": {
                        "svgUrl": "https://wise.com/public-resources/assets/logos/wise/brand_logo_inverse.svg",
                        "pngUrl": "https://wise.com/public-resources/assets/logos/wise/brand_logo_inverse.png"
                    },
                    "white": {
                        "svgUrl": "https://wise.com/public-resources/assets/logos/wise/brand_logo_white.svg",
                        "pngUrl": "https://wise.com/public-resources/assets/logos/wise/brand_logo_white.png"
                    }
                },
                "type": "moneyTransferProvider",
                "partner": false,
                "quotes": [
                    {
                        "rate": 5.67026,
                        "fee": 1.78,
                        "receivedAmount": 556.93,
                        "dateCollected": "2023-01-24T07:58:04Z",
                        "sourceCountry": null,
                        "targetCountry": null,
                        "markup": 0.0,
                        "deliveryEstimation": {
                            "duration": {
                                "min": "PT9H1M55.309554613S",
                                "max": "PT9H1M55.309554613S"
                            },
                            "providerGivesEstimate": true
                        }
                    }
                ]
            },
            {
                "id": 6,
                "alias": "paypal",
                "name": "PayPal",
                "logo": "https://dq8dwmysp7hk1.cloudfront.net/logos/paypal.svg",
                "logos": {
                    "normal": {
                        "svgUrl": "https://dq8dwmysp7hk1.cloudfront.net/logos/paypal.svg",
                        "pngUrl": "https://dq8dwmysp7hk1.cloudfront.net/logos/paypal.png"
                    },
                    "inverse": {
                        "svgUrl": null,
                        "pngUrl": null
                    },
                    "white": {
                        "svgUrl": "https://dq8dwmysp7hk1.cloudfront.net/logos/paypal--white.svg",
                        "pngUrl": "https://dq8dwmysp7hk1.cloudfront.net/logos/paypal--white.png"
                    }
                },
                "type": "moneyTransferProvider",
                "partner": false,
                "quotes": [
                    {
                        "rate": 5.37158506,
                        "fee": 5.0,
                        "receivedAmount": 510.3,
                        "dateCollected": "2023-01-24T07:30:56.464588Z",
                        "sourceCountry": "DE",
                        "targetCountry": "BR",
                        "markup": 5.26739409,
                        "deliveryEstimation": {
                            "duration": null,
                            "providerGivesEstimate": true
                        }
                    }
                ]
            },
            {
                "id": 30,
                "alias": "world-remit",
                "name": "WorldRemit",
                "logo": "https://dq8dwmysp7hk1.cloudfront.net/logos/world-remit.svg",
                "logos": {
                    "normal": {
                        "svgUrl": "https://dq8dwmysp7hk1.cloudfront.net/logos/world-remit.svg",
                        "pngUrl": "https://dq8dwmysp7hk1.cloudfront.net/logos/world-remit.png"
                    },
                    "inverse": {
                        "svgUrl": null,
                        "pngUrl": null
                    },
                    "white": {
                        "svgUrl": "https://dq8dwmysp7hk1.cloudfront.net/logos/world-remit--white.svg",
                        "pngUrl": "https://dq8dwmysp7hk1.cloudfront.net/logos/world-remit--white.png"
                    }
                },
                "type": "moneyTransferProvider",
                "partner": false,
                "quotes": [
                    {
                        "rate": 5.54802768,
                        "fee": 3.99,
                        "receivedAmount": 532.67,
                        "dateCollected": "2023-01-20T13:59:24Z",
                        "sourceCountry": "DE",
                        "targetCountry": "BR",
                        "markup": 2.15567399,
                        "deliveryEstimation": {
                            "duration": {
                                "min": "PT0S",
                                "max": "PT48H"
                            },
                            "providerGivesEstimate": true
                        }
                    }
                ]
            },
            {
                "id": 41,
                "alias": "xoom",
                "name": "Xoom",
                "logo": "https://dq8dwmysp7hk1.cloudfront.net/logos/xoom.svg",
                "logos": {
                    "normal": {
                        "svgUrl": "https://dq8dwmysp7hk1.cloudfront.net/logos/xoom.svg",
                        "pngUrl": "https://dq8dwmysp7hk1.cloudfront.net/logos/xoom.png"
                    },
                    "inverse": {
                        "svgUrl": null,
                        "pngUrl": null
                    },
                    "white": {
                        "svgUrl": "https://dq8dwmysp7hk1.cloudfront.net/logos/xoom--white.svg",
                        "pngUrl": "https://dq8dwmysp7hk1.cloudfront.net/logos/xoom--white.png"
                    }
                },
                "type": "moneyTransferProvider",
                "partner": false,
                "quotes": [
                    {
                        "rate": 5.52831156,
                        "fee": 2.99,
                        "receivedAmount": 536.3,
                        "dateCollected": "2023-01-20T13:06:01Z",
                        "sourceCountry": "DE",
                        "targetCountry": "BR",
                        "markup": 2.50338503,
                        "deliveryEstimation": {
                            "duration": null,
                            "providerGivesEstimate": true
                        }
                    }
                ]
            },
            {
                "id": 22,
                "alias": "western-union",
                "name": "Western Union",
                "logo": "https://dq8dwmysp7hk1.cloudfront.net/logos/western-union.svg",
                "logos": {
                    "normal": {
                        "svgUrl": "https://dq8dwmysp7hk1.cloudfront.net/logos/western-union.svg",
                        "pngUrl": "https://dq8dwmysp7hk1.cloudfront.net/logos/western-union.png"
                    },
                    "inverse": {
                        "svgUrl": null,
                        "pngUrl": null
                    },
                    "white": {
                        "svgUrl": "https://dq8dwmysp7hk1.cloudfront.net/logos/western-union--white.svg",
                        "pngUrl": "https://dq8dwmysp7hk1.cloudfront.net/logos/western-union--white.png"
                    }
                },
                "type": "moneyTransferProvider",
                "partner": false,
                "quotes": [
                    {
                        "rate": 5.47881892,
                        "fee": 0.0,
                        "receivedAmount": 547.88,
                        "dateCollected": "2023-01-20T13:33:42Z",
                        "sourceCountry": "AT",
                        "targetCountry": "BR",
                        "markup": 3.37623107,
                        "deliveryEstimation": {
                            "duration": null,
                            "providerGivesEstimate": true
                        }
                    }
                ]
            },
            {
                "id": 46,
                "alias": "n26",
                "name": "N26",
                "logo": "https://dq8dwmysp7hk1.cloudfront.net/logos/N26.svg",
                "logos": {
                    "normal": {
                        "svgUrl": "https://dq8dwmysp7hk1.cloudfront.net/logos/N26.svg",
                        "pngUrl": "https://dq8dwmysp7hk1.cloudfront.net/logos/N26.png"
                    },
                    "inverse": {
                        "svgUrl": null,
                        "pngUrl": null
                    },
                    "white": {
                        "svgUrl": "https://dq8dwmysp7hk1.cloudfront.net/logos/N26--white.svg",
                        "pngUrl": "https://dq8dwmysp7hk1.cloudfront.net/logos/N26--white.png"
                    }
                },
                "type": "bank",
                "partner": true,
                "quotes": [
                    {
                        "rate": 5.67,
                        "fee": 1.78,
                        "receivedAmount": 556.91,
                        "dateCollected": "2023-01-24T07:57:26Z",
                        "sourceCountry": null,
                        "targetCountry": null,
                        "markup": 0.0,
                        "deliveryEstimation": {
                            "duration": {
                                "min": "PT9H1M55.354204158S",
                                "max": "PT9H1M55.354204158S"
                            },
                            "providerGivesEstimate": true
                        }
                    }
                ]
            },
            {
                "id": 59,
                "alias": "ofx",
                "name": "OFX",
                "logo": "https://dq8dwmysp7hk1.cloudfront.net/logos/ofx.svg",
                "logos": {
                    "normal": {
                        "svgUrl": "https://dq8dwmysp7hk1.cloudfront.net/logos/ofx.svg",
                        "pngUrl": "https://dq8dwmysp7hk1.cloudfront.net/logos/ofx.png"
                    },
                    "inverse": {
                        "svgUrl": null,
                        "pngUrl": null
                    },
                    "white": {
                        "svgUrl": "https://dq8dwmysp7hk1.cloudfront.net/logos/ofx--white.svg",
                        "pngUrl": "https://dq8dwmysp7hk1.cloudfront.net/logos/ofx--white.png"
                    }
                },
                "type": "moneyTransferProvider",
                "partner": false,
                "quotes": [
                    {
                        "rate": 5.31615623,
                        "fee": 0.0,
                        "receivedAmount": 531.62,
                        "dateCollected": "2023-01-24T07:21:37.119802Z",
                        "sourceCountry": null,
                        "targetCountry": null,
                        "markup": 6.24493004,
                        "deliveryEstimation": {
                            "duration": null,
                            "providerGivesEstimate": true
                        }
                    }
                ]
            },
            {
                "id": 23,
                "alias": "moneygram",
                "name": "Moneygram",
                "logo": "https://dq8dwmysp7hk1.cloudfront.net/logos/moneygram.svg",
                "logos": {
                    "normal": {
                        "svgUrl": "https://dq8dwmysp7hk1.cloudfront.net/logos/moneygram.svg",
                        "pngUrl": "https://dq8dwmysp7hk1.cloudfront.net/logos/moneygram.png"
                    },
                    "inverse": {
                        "svgUrl": null,
                        "pngUrl": null
                    },
                    "white": {
                        "svgUrl": "https://dq8dwmysp7hk1.cloudfront.net/logos/moneygram--white.svg",
                        "pngUrl": "https://dq8dwmysp7hk1.cloudfront.net/logos/moneygram--white.png"
                    }
                },
                "type": "moneyTransferProvider",
                "partner": false,
                "quotes": [
                    {
                        "rate": 5.65286364,
                        "fee": 4.5,
                        "receivedAmount": 539.85,
                        "dateCollected": "2023-01-23T23:01:23Z",
                        "sourceCountry": "DE",
                        "targetCountry": "BR",
                        "markup": 0.30680004,
                        "deliveryEstimation": {
                            "duration": {
                                "min": "PT0S",
                                "max": "PT96H"
                            },
                            "providerGivesEstimate": true
                        }
                    }
                ]
            }
        ]
    },
    "CLP": {
        "sourceCurrency": "EUR",
        "targetCurrency": "CLP",
        "sourceCountry": null,
        "targetCountry": null,
        "providerCountry": null,
        "providerType": null,
        "sendAmount": 100.0,
        "providers": [
            {
                "id": 104,
                "alias": "remitly",
                "name": "Remitly",
                "logo": "https://dq8dwmysp7hk1.cloudfront.net/logos/remitly.svg",
                "logos": {
                    "normal": {
                        "svgUrl": "https://dq8dwmysp7hk1.cloudfront.net/logos/remitly.svg",
                        "pngUrl": "https://dq8dwmysp7hk1.cloudfront.net/logos/remitly.png"
                    },
                    "inverse": {
                        "svgUrl": null,
                        "pngUrl": null
                    },
                    "white": {
                        "svgUrl": "https://dq8dwmysp7hk1.cloudfront.net/logos/remitly--white.svg",
                        "pngUrl": "https://dq8dwmysp7hk1.cloudfront.net/logos/remitly--white.png"
                    }
                },
                "type": "moneyTransferProvider",
                "partner": false,
                "quotes": [
                    {
                        "rate": 871.2905211,
                        "fee": 4.99,
                        "receivedAmount": 82781.31,
                        "dateCollected": "2023-01-24T07:43:36.779283Z",
                        "sourceCountry": "DE",
                        "targetCountry": "CL",
                        "markup": 1.613684,
                        "deliveryEstimation": {
                            "duration": null,
                            "providerGivesEstimate": true
                        }
                    }
                ]
            },
            {
                "id": 39,
                "alias": "wise",
                "name": "Wise",
                "logo": "https://wise.com/public-resources/assets/logos/wise/brand_logo.svg",
                "logos": {
                    "normal": {
                        "svgUrl": "https://wise.com/public-resources/assets/logos/wise/brand_logo.svg",
                        "pngUrl": "https://wise.com/public-resources/assets/logos/wise/brand_logo.png"
                    },
                    "inverse": {
                        "svgUrl": "https://wise.com/public-resources/assets/logos/wise/brand_logo_inverse.svg",
                        "pngUrl": "https://wise.com/public-resources/assets/logos/wise/brand_logo_inverse.png"
                    },
                    "white": {
                        "svgUrl": "https://wise.com/public-resources/assets/logos/wise/brand_logo_white.svg",
                        "pngUrl": "https://wise.com/public-resources/assets/logos/wise/brand_logo_white.png"
                    }
                },
                "type": "moneyTransferProvider",
                "partner": false,
                "quotes": [
                    {
                        "rate": 885.581,
                        "fee": 3.38,
                        "receivedAmount": 85564.84,
                        "dateCollected": "2023-01-24T08:01:11Z",
                        "sourceCountry": null,
                        "targetCountry": null,
                        "markup": 0.0,
                        "deliveryEstimation": {
                            "duration": {
                                "min": "PT76H58M48.583448007S",
                                "max": "PT76H58M48.583448007S"
                            },
                            "providerGivesEstimate": true
                        }
                    }
                ]
            }
        ]
    },
    "COP": {
        "sourceCurrency": "EUR",
        "targetCurrency": "COP",
        "sourceCountry": null,
        "targetCountry": null,
        "providerCountry": null,
        "providerType": null,
        "sendAmount": 100.0,
        "providers": [
            {
                "id": 7,
                "alias": "bbva",
                "name": "BBVA",
                "logo": "https://dq8dwmysp7hk1.cloudfront.net/logos/bbva.svg",
                "logos": {
                    "normal": {
                        "svgUrl": "https://dq8dwmysp7hk1.cloudfront.net/logos/bbva.svg",
                        "pngUrl": "https://dq8dwmysp7hk1.cloudfront.net/logos/bbva.png"
                    },
                    "inverse": {
                        "svgUrl": null,
                        "pngUrl": null
                    },
                    "white": {
                        "svgUrl": "https://dq8dwmysp7hk1.cloudfront.net/logos/bbva--white.svg",
                        "pngUrl": "https://dq8dwmysp7hk1.cloudfront.net/logos/bbva--white.png"
                    }
                },
                "type": "bank",
                "partner": false,
                "quotes": [
                    {
                        "rate": 4800.79725485,
                        "fee": 45.0,
                        "receivedAmount": 264043.85,
                        "dateCollected": "2023-01-24T07:50:09.863660Z",
                        "sourceCountry": "ES",
                        "targetCountry": null,
                        "markup": 3.293571,
                        "deliveryEstimation": {
                            "duration": null,
                            "providerGivesEstimate": true
                        }
                    }
                ]
            },
            {
                "id": 104,
                "alias": "remitly",
                "name": "Remitly",
                "logo": "https://dq8dwmysp7hk1.cloudfront.net/logos/remitly.svg",
                "logos": {
                    "normal": {
                        "svgUrl": "https://dq8dwmysp7hk1.cloudfront.net/logos/remitly.svg",
                        "pngUrl": "https://dq8dwmysp7hk1.cloudfront.net/logos/remitly.png"
                    },
                    "inverse": {
                        "svgUrl": null,
                        "pngUrl": null
                    },
                    "white": {
                        "svgUrl": "https://dq8dwmysp7hk1.cloudfront.net/logos/remitly--white.svg",
                        "pngUrl": "https://dq8dwmysp7hk1.cloudfront.net/logos/remitly--white.png"
                    }
                },
                "type": "moneyTransferProvider",
                "partner": false,
                "quotes": [
                    {
                        "rate": 4871.7551719,
                        "fee": 2.99,
                        "receivedAmount": 472608.97,
                        "dateCollected": "2023-01-24T07:43:39.213883Z",
                        "sourceCountry": "DE",
                        "targetCountry": "CO",
                        "markup": 1.864207,
                        "deliveryEstimation": {
                            "duration": null,
                            "providerGivesEstimate": true
                        }
                    }
                ]
            },
            {
                "id": 39,
                "alias": "wise",
                "name": "Wise",
                "logo": "https://wise.com/public-resources/assets/logos/wise/brand_logo.svg",
                "logos": {
                    "normal": {
                        "svgUrl": "https://wise.com/public-resources/assets/logos/wise/brand_logo.svg",
                        "pngUrl": "https://wise.com/public-resources/assets/logos/wise/brand_logo.png"
                    },
                    "inverse": {
                        "svgUrl": "https://wise.com/public-resources/assets/logos/wise/brand_logo_inverse.svg",
                        "pngUrl": "https://wise.com/public-resources/assets/logos/wise/brand_logo_inverse.png"
                    },
                    "white": {
                        "svgUrl": "https://wise.com/public-resources/assets/logos/wise/brand_logo_white.svg",
                        "pngUrl": "https://wise.com/public-resources/assets/logos/wise/brand_logo_white.png"
                    }
                },
                "type": "moneyTransferProvider",
                "partner": false,
                "quotes": [
                    {
                        "rate": 4964.3,
                        "fee": 3.18,
                        "receivedAmount": 480643.53,
                        "dateCollected": "2023-01-24T08:01:11Z",
                        "sourceCountry": null,
                        "targetCountry": null,
                        "markup": 0.0,
                        "deliveryEstimation": {
                            "duration": {
                                "min": "PT4H56M59.198566153S",
                                "max": "PT4H56M59.198566153S"
                            },
                            "providerGivesEstimate": true
                        }
                    }
                ]
            }
        ]
    },
    "CRC": {
        "sourceCurrency": "EUR",
        "targetCurrency": "CRC",
        "sourceCountry": null,
        "targetCountry": null,
        "providerCountry": null,
        "providerType": null,
        "sendAmount": 100.0,
        "providers": [
            {
                "id": 39,
                "alias": "wise",
                "name": "Wise",
                "logo": "https://wise.com/public-resources/assets/logos/wise/brand_logo.svg",
                "logos": {
                    "normal": {
                        "svgUrl": "https://wise.com/public-resources/assets/logos/wise/brand_logo.svg",
                        "pngUrl": "https://wise.com/public-resources/assets/logos/wise/brand_logo.png"
                    },
                    "inverse": {
                        "svgUrl": "https://wise.com/public-resources/assets/logos/wise/brand_logo_inverse.svg",
                        "pngUrl": "https://wise.com/public-resources/assets/logos/wise/brand_logo_inverse.png"
                    },
                    "white": {
                        "svgUrl": "https://wise.com/public-resources/assets/logos/wise/brand_logo_white.svg",
                        "pngUrl": "https://wise.com/public-resources/assets/logos/wise/brand_logo_white.png"
                    }
                },
                "type": "moneyTransferProvider",
                "partner": false,
                "quotes": [
                    {
                        "rate": 613.377,
                        "fee": 5.51,
                        "receivedAmount": 57957.99,
                        "dateCollected": "2023-01-24T08:01:12Z",
                        "sourceCountry": null,
                        "targetCountry": null,
                        "markup": 0.0,
                        "deliveryEstimation": {
                            "duration": {
                                "min": "PT39H58M47.777757373S",
                                "max": "PT39H58M47.777757373S"
                            },
                            "providerGivesEstimate": true
                        }
                    }
                ]
            },
            {
                "id": 46,
                "alias": "n26",
                "name": "N26",
                "logo": "https://dq8dwmysp7hk1.cloudfront.net/logos/N26.svg",
                "logos": {
                    "normal": {
                        "svgUrl": "https://dq8dwmysp7hk1.cloudfront.net/logos/N26.svg",
                        "pngUrl": "https://dq8dwmysp7hk1.cloudfront.net/logos/N26.png"
                    },
                    "inverse": {
                        "svgUrl": null,
                        "pngUrl": null
                    },
                    "white": {
                        "svgUrl": "https://dq8dwmysp7hk1.cloudfront.net/logos/N26--white.svg",
                        "pngUrl": "https://dq8dwmysp7hk1.cloudfront.net/logos/N26--white.png"
                    }
                },
                "type": "bank",
                "partner": true,
                "quotes": [
                    {
                        "rate": 613.377,
                        "fee": 5.51,
                        "receivedAmount": 57957.99,
                        "dateCollected": "2023-01-24T08:01:12Z",
                        "sourceCountry": null,
                        "targetCountry": null,
                        "markup": 0.0,
                        "deliveryEstimation": {
                            "duration": {
                                "min": "PT39H58M47.777132245S",
                                "max": "PT39H58M47.777132245S"
                            },
                            "providerGivesEstimate": true
                        }
                    }
                ]
            },
            {
                "id": 104,
                "alias": "remitly",
                "name": "Remitly",
                "logo": "https://dq8dwmysp7hk1.cloudfront.net/logos/remitly.svg",
                "logos": {
                    "normal": {
                        "svgUrl": "https://dq8dwmysp7hk1.cloudfront.net/logos/remitly.svg",
                        "pngUrl": "https://dq8dwmysp7hk1.cloudfront.net/logos/remitly.png"
                    },
                    "inverse": {
                        "svgUrl": null,
                        "pngUrl": null
                    },
                    "white": {
                        "svgUrl": "https://dq8dwmysp7hk1.cloudfront.net/logos/remitly--white.svg",
                        "pngUrl": "https://dq8dwmysp7hk1.cloudfront.net/logos/remitly--white.png"
                    }
                },
                "type": "moneyTransferProvider",
                "partner": false,
                "quotes": [
                    {
                        "rate": 588.55785284,
                        "fee": 3.99,
                        "receivedAmount": 56507.44,
                        "dateCollected": "2023-01-24T07:43:40.559186Z",
                        "sourceCountry": "DE",
                        "targetCountry": "CR",
                        "markup": 4.046312,
                        "deliveryEstimation": {
                            "duration": null,
                            "providerGivesEstimate": true
                        }
                    }
                ]
            }
        ]
    },
    "CUP": {
        "sourceCurrency": "EUR",
        "targetCurrency": "CUP",
        "sourceCountry": null,
        "targetCountry": null,
        "providerCountry": null,
        "providerType": null,
        "sendAmount": 100.0,
        "providers": []
    },
    "DOP": {
        "sourceCurrency": "EUR",
        "targetCurrency": "DOP",
        "sourceCountry": null,
        "targetCountry": null,
        "providerCountry": null,
        "providerType": null,
        "sendAmount": 100.0,
        "providers": []
    },
    "GTQ": {
        "sourceCurrency": "EUR",
        "targetCurrency": "GTQ",
        "sourceCountry": null,
        "targetCountry": null,
        "providerCountry": null,
        "providerType": null,
        "sendAmount": 100.0,
        "providers": []
    },
    "HNL": {
        "sourceCurrency": "EUR",
        "targetCurrency": "HNL",
        "sourceCountry": null,
        "targetCountry": null,
        "providerCountry": null,
        "providerType": null,
        "sendAmount": 100.0,
        "providers": []
    },
    "MXN": {
        "sourceCurrency": "EUR",
        "targetCurrency": "MXN",
        "sourceCountry": null,
        "targetCountry": null,
        "providerCountry": null,
        "providerType": null,
        "sendAmount": 100.0,
        "providers": [
            {
                "id": 45,
                "alias": "bunq",
                "name": "bunq",
                "logo": "https://dq8dwmysp7hk1.cloudfront.net/logos/bunq.svg",
                "logos": {
                    "normal": {
                        "svgUrl": "https://dq8dwmysp7hk1.cloudfront.net/logos/bunq.svg",
                        "pngUrl": "https://dq8dwmysp7hk1.cloudfront.net/logos/bunq.png"
                    },
                    "inverse": {
                        "svgUrl": null,
                        "pngUrl": null
                    },
                    "white": {
                        "svgUrl": "https://dq8dwmysp7hk1.cloudfront.net/logos/bunq--white.svg",
                        "pngUrl": "https://dq8dwmysp7hk1.cloudfront.net/logos/bunq--white.png"
                    }
                },
                "type": "bank",
                "partner": true,
                "quotes": [
                    {
                        "rate": 20.4767,
                        "fee": 1.09,
                        "receivedAmount": 2025.35,
                        "dateCollected": "2023-01-24T08:01:13Z",
                        "sourceCountry": null,
                        "targetCountry": null,
                        "markup": 0.0,
                        "deliveryEstimation": {
                            "duration": {
                                "min": "PT4H56M59.058795082S",
                                "max": "PT4H56M59.058795082S"
                            },
                            "providerGivesEstimate": true
                        }
                    }
                ]
            },
            {
                "id": 59,
                "alias": "ofx",
                "name": "OFX",
                "logo": "https://dq8dwmysp7hk1.cloudfront.net/logos/ofx.svg",
                "logos": {
                    "normal": {
                        "svgUrl": "https://dq8dwmysp7hk1.cloudfront.net/logos/ofx.svg",
                        "pngUrl": "https://dq8dwmysp7hk1.cloudfront.net/logos/ofx.png"
                    },
                    "inverse": {
                        "svgUrl": null,
                        "pngUrl": null
                    },
                    "white": {
                        "svgUrl": "https://dq8dwmysp7hk1.cloudfront.net/logos/ofx--white.svg",
                        "pngUrl": "https://dq8dwmysp7hk1.cloudfront.net/logos/ofx--white.png"
                    }
                },
                "type": "moneyTransferProvider",
                "partner": false,
                "quotes": [
                    {
                        "rate": 20.18221147,
                        "fee": 0.0,
                        "receivedAmount": 2018.22,
                        "dateCollected": "2023-01-24T07:22:52.931848Z",
                        "sourceCountry": null,
                        "targetCountry": null,
                        "markup": 1.43816401,
                        "deliveryEstimation": {
                            "duration": null,
                            "providerGivesEstimate": true
                        }
                    }
                ]
            },
            {
                "id": 10,
                "alias": "sabadell",
                "name": "Sabadell",
                "logo": "https://dq8dwmysp7hk1.cloudfront.net/logos/sabadell.svg",
                "logos": {
                    "normal": {
                        "svgUrl": "https://dq8dwmysp7hk1.cloudfront.net/logos/sabadell.svg",
                        "pngUrl": "https://dq8dwmysp7hk1.cloudfront.net/logos/sabadell.png"
                    },
                    "inverse": {
                        "svgUrl": null,
                        "pngUrl": null
                    },
                    "white": {
                        "svgUrl": "https://dq8dwmysp7hk1.cloudfront.net/logos/sabadell--white.svg",
                        "pngUrl": "https://dq8dwmysp7hk1.cloudfront.net/logos/sabadell--white.png"
                    }
                },
                "type": "bank",
                "partner": false,
                "quotes": [
                    {
                        "rate": 19.83599122,
                        "fee": 22.0,
                        "receivedAmount": 1547.21,
                        "dateCollected": "2023-01-24T07:40:02.021254Z",
                        "sourceCountry": "ES",
                        "targetCountry": null,
                        "markup": 3.12896502,
                        "deliveryEstimation": {
                            "duration": null,
                            "providerGivesEstimate": false
                        }
                    }
                ]
            },
            {
                "id": 23,
                "alias": "moneygram",
                "name": "Moneygram",
                "logo": "https://dq8dwmysp7hk1.cloudfront.net/logos/moneygram.svg",
                "logos": {
                    "normal": {
                        "svgUrl": "https://dq8dwmysp7hk1.cloudfront.net/logos/moneygram.svg",
                        "pngUrl": "https://dq8dwmysp7hk1.cloudfront.net/logos/moneygram.png"
                    },
                    "inverse": {
                        "svgUrl": null,
                        "pngUrl": null
                    },
                    "white": {
                        "svgUrl": "https://dq8dwmysp7hk1.cloudfront.net/logos/moneygram--white.svg",
                        "pngUrl": "https://dq8dwmysp7hk1.cloudfront.net/logos/moneygram--white.png"
                    }
                },
                "type": "moneyTransferProvider",
                "partner": false,
                "quotes": [
                    {
                        "rate": 20.61079249,
                        "fee": 4.5,
                        "receivedAmount": 1968.33,
                        "dateCollected": "2023-01-23T23:09:08Z",
                        "sourceCountry": "DE",
                        "targetCountry": "MX",
                        "markup": -0.654854,
                        "deliveryEstimation": {
                            "duration": {
                                "min": "PT1H",
                                "max": "PT96H"
                            },
                            "providerGivesEstimate": true
                        }
                    }
                ]
            },
            {
                "id": 9,
                "alias": "lacaixa",
                "name": "LaCaixa",
                "logo": "https://dq8dwmysp7hk1.cloudfront.net/logos/caixa-bank.svg",
                "logos": {
                    "normal": {
                        "svgUrl": "https://dq8dwmysp7hk1.cloudfront.net/logos/caixa-bank.svg",
                        "pngUrl": "https://dq8dwmysp7hk1.cloudfront.net/logos/caixa-bank.png"
                    },
                    "inverse": {
                        "svgUrl": null,
                        "pngUrl": null
                    },
                    "white": {
                        "svgUrl": "https://dq8dwmysp7hk1.cloudfront.net/logos/caixa-bank--white.svg",
                        "pngUrl": "https://dq8dwmysp7hk1.cloudfront.net/logos/caixa-bank--white.png"
                    }
                },
                "type": "bank",
                "partner": false,
                "quotes": [
                    {
                        "rate": 19.98702818,
                        "fee": 27.0,
                        "receivedAmount": 1459.05,
                        "dateCollected": "2023-01-24T07:20:03.972761Z",
                        "sourceCountry": "ES",
                        "targetCountry": null,
                        "markup": 2.39136101,
                        "deliveryEstimation": {
                            "duration": {
                                "min": "PT24H",
                                "max": "PT24H"
                            },
                            "providerGivesEstimate": true
                        }
                    }
                ]
            },
            {
                "id": 110,
                "alias": "abn-amro-bank",
                "name": "ABN AMRO Bank",
                "logo": "https://dq8dwmysp7hk1.cloudfront.net/logos/abn-amro-bank.svg",
                "logos": {
                    "normal": {
                        "svgUrl": "https://dq8dwmysp7hk1.cloudfront.net/logos/abn-amro-bank.svg",
                        "pngUrl": "https://dq8dwmysp7hk1.cloudfront.net/logos/abn-amro-bank.png"
                    },
                    "inverse": {
                        "svgUrl": null,
                        "pngUrl": null
                    },
                    "white": {
                        "svgUrl": "https://dq8dwmysp7hk1.cloudfront.net/logos/abn-amro-bank--white.svg",
                        "pngUrl": "https://dq8dwmysp7hk1.cloudfront.net/logos/abn-amro-bank--white.png"
                    }
                },
                "type": "bank",
                "partner": false,
                "quotes": [
                    {
                        "rate": 20.10210437,
                        "fee": 9.0,
                        "receivedAmount": 1829.29,
                        "dateCollected": "2023-01-24T07:50:02.836891Z",
                        "sourceCountry": "NL",
                        "targetCountry": "MX",
                        "markup": 1.829375,
                        "deliveryEstimation": {
                            "duration": null,
                            "providerGivesEstimate": true
                        }
                    }
                ]
            },
            {
                "id": 43,
                "alias": "ing-nl",
                "name": "ING",
                "logo": "https://dq8dwmysp7hk1.cloudfront.net/logos/ingnl.svg",
                "logos": {
                    "normal": {
                        "svgUrl": "https://dq8dwmysp7hk1.cloudfront.net/logos/ingnl.svg",
                        "pngUrl": "https://dq8dwmysp7hk1.cloudfront.net/logos/ingnl.png"
                    },
                    "inverse": {
                        "svgUrl": null,
                        "pngUrl": null
                    },
                    "white": {
                        "svgUrl": "https://dq8dwmysp7hk1.cloudfront.net/logos/ingnl--white.svg",
                        "pngUrl": "https://dq8dwmysp7hk1.cloudfront.net/logos/ingnl--white.png"
                    }
                },
                "type": "bank",
                "partner": false,
                "quotes": [
                    {
                        "rate": 20.4767,
                        "fee": 36.0,
                        "receivedAmount": 1310.51,
                        "dateCollected": "2023-01-24T07:20:01.040755Z",
                        "sourceCountry": "NL",
                        "targetCountry": "MX",
                        "markup": 0.0,
                        "deliveryEstimation": {
                            "duration": {
                                "min": "PT48H",
                                "max": "PT72H"
                            },
                            "providerGivesEstimate": true
                        }
                    }
                ]
            },
            {
                "id": 121,
                "alias": "xe",
                "name": "Xe",
                "logo": "https://dq8dwmysp7hk1.cloudfront.net/logos/xe.svg",
                "logos": {
                    "normal": {
                        "svgUrl": "https://dq8dwmysp7hk1.cloudfront.net/logos/xe.svg",
                        "pngUrl": "https://dq8dwmysp7hk1.cloudfront.net/logos/xe.png"
                    },
                    "inverse": {
                        "svgUrl": null,
                        "pngUrl": null
                    },
                    "white": {
                        "svgUrl": "https://dq8dwmysp7hk1.cloudfront.net/logos/xe--white.svg",
                        "pngUrl": "https://dq8dwmysp7hk1.cloudfront.net/logos/xe--white.png"
                    }
                },
                "type": "moneyTransferProvider",
                "partner": false,
                "quotes": [
                    {
                        "rate": 20.19991358,
                        "fee": 2.0,
                        "receivedAmount": 1979.59,
                        "dateCollected": "2023-01-20T14:45:02Z",
                        "sourceCountry": "DE",
                        "targetCountry": "MX",
                        "markup": 1.351714,
                        "deliveryEstimation": {
                            "duration": null,
                            "providerGivesEstimate": true
                        }
                    }
                ]
            },
            {
                "id": 7,
                "alias": "bbva",
                "name": "BBVA",
                "logo": "https://dq8dwmysp7hk1.cloudfront.net/logos/bbva.svg",
                "logos": {
                    "normal": {
                        "svgUrl": "https://dq8dwmysp7hk1.cloudfront.net/logos/bbva.svg",
                        "pngUrl": "https://dq8dwmysp7hk1.cloudfront.net/logos/bbva.png"
                    },
                    "inverse": {
                        "svgUrl": null,
                        "pngUrl": null
                    },
                    "white": {
                        "svgUrl": "https://dq8dwmysp7hk1.cloudfront.net/logos/bbva--white.svg",
                        "pngUrl": "https://dq8dwmysp7hk1.cloudfront.net/logos/bbva--white.png"
                    }
                },
                "type": "bank",
                "partner": false,
                "quotes": [
                    {
                        "rate": 19.82809561,
                        "fee": 45.0,
                        "receivedAmount": 1090.55,
                        "dateCollected": "2023-01-24T07:50:09.863822Z",
                        "sourceCountry": "ES",
                        "targetCountry": null,
                        "markup": 3.16752402,
                        "deliveryEstimation": {
                            "duration": null,
                            "providerGivesEstimate": true
                        }
                    },
                    {
                        "rate": 19.82809561,
                        "fee": 45.0,
                        "receivedAmount": 1090.55,
                        "dateCollected": "2023-01-24T07:50:09.863822Z",
                        "sourceCountry": "ES",
                        "targetCountry": "MX",
                        "markup": 3.16752402,
                        "deliveryEstimation": {
                            "duration": {
                                "min": null,
                                "max": "PT96H"
                            },
                            "providerGivesEstimate": true
                        }
                    }
                ]
            },
            {
                "id": 104,
                "alias": "remitly",
                "name": "Remitly",
                "logo": "https://dq8dwmysp7hk1.cloudfront.net/logos/remitly.svg",
                "logos": {
                    "normal": {
                        "svgUrl": "https://dq8dwmysp7hk1.cloudfront.net/logos/remitly.svg",
                        "pngUrl": "https://dq8dwmysp7hk1.cloudfront.net/logos/remitly.png"
                    },
                    "inverse": {
                        "svgUrl": null,
                        "pngUrl": null
                    },
                    "white": {
                        "svgUrl": "https://dq8dwmysp7hk1.cloudfront.net/logos/remitly--white.svg",
                        "pngUrl": "https://dq8dwmysp7hk1.cloudfront.net/logos/remitly--white.png"
                    }
                },
                "type": "moneyTransferProvider",
                "partner": false,
                "quotes": [
                    {
                        "rate": 19.9987685,
                        "fee": 4.49,
                        "receivedAmount": 1910.08,
                        "dateCollected": "2023-01-24T07:43:55.190576Z",
                        "sourceCountry": "DE",
                        "targetCountry": "MX",
                        "markup": 2.33402599,
                        "deliveryEstimation": {
                            "duration": null,
                            "providerGivesEstimate": true
                        }
                    }
                ]
            },
            {
                "id": 46,
                "alias": "n26",
                "name": "N26",
                "logo": "https://dq8dwmysp7hk1.cloudfront.net/logos/N26.svg",
                "logos": {
                    "normal": {
                        "svgUrl": "https://dq8dwmysp7hk1.cloudfront.net/logos/N26.svg",
                        "pngUrl": "https://dq8dwmysp7hk1.cloudfront.net/logos/N26.png"
                    },
                    "inverse": {
                        "svgUrl": null,
                        "pngUrl": null
                    },
                    "white": {
                        "svgUrl": "https://dq8dwmysp7hk1.cloudfront.net/logos/N26--white.svg",
                        "pngUrl": "https://dq8dwmysp7hk1.cloudfront.net/logos/N26--white.png"
                    }
                },
                "type": "bank",
                "partner": true,
                "quotes": [
                    {
                        "rate": 20.4767,
                        "fee": 1.09,
                        "receivedAmount": 2025.35,
                        "dateCollected": "2023-01-24T08:01:13Z",
                        "sourceCountry": null,
                        "targetCountry": null,
                        "markup": 0.0,
                        "deliveryEstimation": {
                            "duration": {
                                "min": "PT4H56M59.006874837S",
                                "max": "PT4H56M59.006874837S"
                            },
                            "providerGivesEstimate": true
                        }
                    }
                ]
            },
            {
                "id": 22,
                "alias": "western-union",
                "name": "Western Union",
                "logo": "https://dq8dwmysp7hk1.cloudfront.net/logos/western-union.svg",
                "logos": {
                    "normal": {
                        "svgUrl": "https://dq8dwmysp7hk1.cloudfront.net/logos/western-union.svg",
                        "pngUrl": "https://dq8dwmysp7hk1.cloudfront.net/logos/western-union.png"
                    },
                    "inverse": {
                        "svgUrl": null,
                        "pngUrl": null
                    },
                    "white": {
                        "svgUrl": "https://dq8dwmysp7hk1.cloudfront.net/logos/western-union--white.svg",
                        "pngUrl": "https://dq8dwmysp7hk1.cloudfront.net/logos/western-union--white.png"
                    }
                },
                "type": "moneyTransferProvider",
                "partner": false,
                "quotes": [
                    {
                        "rate": 20.2139606,
                        "fee": 0.0,
                        "receivedAmount": 2021.4,
                        "dateCollected": "2023-01-20T13:41:03Z",
                        "sourceCountry": "AT",
                        "targetCountry": "MX",
                        "markup": 1.28311398,
                        "deliveryEstimation": {
                            "duration": null,
                            "providerGivesEstimate": true
                        }
                    }
                ]
            },
            {
                "id": 30,
                "alias": "world-remit",
                "name": "WorldRemit",
                "logo": "https://dq8dwmysp7hk1.cloudfront.net/logos/world-remit.svg",
                "logos": {
                    "normal": {
                        "svgUrl": "https://dq8dwmysp7hk1.cloudfront.net/logos/world-remit.svg",
                        "pngUrl": "https://dq8dwmysp7hk1.cloudfront.net/logos/world-remit.png"
                    },
                    "inverse": {
                        "svgUrl": null,
                        "pngUrl": null
                    },
                    "white": {
                        "svgUrl": "https://dq8dwmysp7hk1.cloudfront.net/logos/world-remit--white.svg",
                        "pngUrl": "https://dq8dwmysp7hk1.cloudfront.net/logos/world-remit--white.png"
                    }
                },
                "type": "moneyTransferProvider",
                "partner": false,
                "quotes": [
                    {
                        "rate": 20.27748833,
                        "fee": 3.99,
                        "receivedAmount": 1946.84,
                        "dateCollected": "2023-01-20T14:00:46Z",
                        "sourceCountry": "DE",
                        "targetCountry": "MX",
                        "markup": 0.97286999,
                        "deliveryEstimation": {
                            "duration": {
                                "min": "PT0S",
                                "max": "PT2H"
                            },
                            "providerGivesEstimate": true
                        }
                    }
                ]
            },
            {
                "id": 39,
                "alias": "wise",
                "name": "Wise",
                "logo": "https://wise.com/public-resources/assets/logos/wise/brand_logo.svg",
                "logos": {
                    "normal": {
                        "svgUrl": "https://wise.com/public-resources/assets/logos/wise/brand_logo.svg",
                        "pngUrl": "https://wise.com/public-resources/assets/logos/wise/brand_logo.png"
                    },
                    "inverse": {
                        "svgUrl": "https://wise.com/public-resources/assets/logos/wise/brand_logo_inverse.svg",
                        "pngUrl": "https://wise.com/public-resources/assets/logos/wise/brand_logo_inverse.png"
                    },
                    "white": {
                        "svgUrl": "https://wise.com/public-resources/assets/logos/wise/brand_logo_white.svg",
                        "pngUrl": "https://wise.com/public-resources/assets/logos/wise/brand_logo_white.png"
                    }
                },
                "type": "moneyTransferProvider",
                "partner": false,
                "quotes": [
                    {
                        "rate": 20.4767,
                        "fee": 1.09,
                        "receivedAmount": 2025.35,
                        "dateCollected": "2023-01-24T08:01:13Z",
                        "sourceCountry": null,
                        "targetCountry": null,
                        "markup": 0.0,
                        "deliveryEstimation": {
                            "duration": {
                                "min": "PT4H56M59.04964253S",
                                "max": "PT4H56M59.04964253S"
                            },
                            "providerGivesEstimate": true
                        }
                    }
                ]
            },
            {
                "id": 41,
                "alias": "xoom",
                "name": "Xoom",
                "logo": "https://dq8dwmysp7hk1.cloudfront.net/logos/xoom.svg",
                "logos": {
                    "normal": {
                        "svgUrl": "https://dq8dwmysp7hk1.cloudfront.net/logos/xoom.svg",
                        "pngUrl": "https://dq8dwmysp7hk1.cloudfront.net/logos/xoom.png"
                    },
                    "inverse": {
                        "svgUrl": null,
                        "pngUrl": null
                    },
                    "white": {
                        "svgUrl": "https://dq8dwmysp7hk1.cloudfront.net/logos/xoom--white.svg",
                        "pngUrl": "https://dq8dwmysp7hk1.cloudfront.net/logos/xoom--white.png"
                    }
                },
                "type": "moneyTransferProvider",
                "partner": false,
                "quotes": [
                    {
                        "rate": 20.07901935,
                        "fee": 2.99,
                        "receivedAmount": 1947.87,
                        "dateCollected": "2023-01-20T13:12:27Z",
                        "sourceCountry": "DE",
                        "targetCountry": "MX",
                        "markup": 1.94211299,
                        "deliveryEstimation": {
                            "duration": null,
                            "providerGivesEstimate": true
                        }
                    }
                ]
            },
            {
                "id": 6,
                "alias": "paypal",
                "name": "PayPal",
                "logo": "https://dq8dwmysp7hk1.cloudfront.net/logos/paypal.svg",
                "logos": {
                    "normal": {
                        "svgUrl": "https://dq8dwmysp7hk1.cloudfront.net/logos/paypal.svg",
                        "pngUrl": "https://dq8dwmysp7hk1.cloudfront.net/logos/paypal.png"
                    },
                    "inverse": {
                        "svgUrl": null,
                        "pngUrl": null
                    },
                    "white": {
                        "svgUrl": "https://dq8dwmysp7hk1.cloudfront.net/logos/paypal--white.svg",
                        "pngUrl": "https://dq8dwmysp7hk1.cloudfront.net/logos/paypal--white.png"
                    }
                },
                "type": "moneyTransferProvider",
                "partner": false,
                "quotes": [
                    {
                        "rate": 19.54515042,
                        "fee": 5.0,
                        "receivedAmount": 1856.79,
                        "dateCollected": "2023-01-24T07:31:22.203618Z",
                        "sourceCountry": "DE",
                        "targetCountry": "MX",
                        "markup": 4.54931498,
                        "deliveryEstimation": {
                            "duration": null,
                            "providerGivesEstimate": true
                        }
                    }
                ]
            }
        ]
    },
    "NIO": {
        "sourceCurrency": "EUR",
        "targetCurrency": "NIO",
        "sourceCountry": null,
        "targetCountry": null,
        "providerCountry": null,
        "providerType": null,
        "sendAmount": 100.0,
        "providers": []
    },
    "PAB": {
        "sourceCurrency": "EUR",
        "targetCurrency": "PAB",
        "sourceCountry": null,
        "targetCountry": null,
        "providerCountry": null,
        "providerType": null,
        "sendAmount": 100.0,
        "providers": []
    },
    "PEN": {
        "sourceCurrency": "EUR",
        "targetCurrency": "PEN",
        "sourceCountry": null,
        "targetCountry": null,
        "providerCountry": null,
        "providerType": null,
        "sendAmount": 100.0,
        "providers": [
            {
                "id": 104,
                "alias": "remitly",
                "name": "Remitly",
                "logo": "https://dq8dwmysp7hk1.cloudfront.net/logos/remitly.svg",
                "logos": {
                    "normal": {
                        "svgUrl": "https://dq8dwmysp7hk1.cloudfront.net/logos/remitly.svg",
                        "pngUrl": "https://dq8dwmysp7hk1.cloudfront.net/logos/remitly.png"
                    },
                    "inverse": {
                        "svgUrl": null,
                        "pngUrl": null
                    },
                    "white": {
                        "svgUrl": "https://dq8dwmysp7hk1.cloudfront.net/logos/remitly--white.svg",
                        "pngUrl": "https://dq8dwmysp7hk1.cloudfront.net/logos/remitly--white.png"
                    }
                },
                "type": "moneyTransferProvider",
                "partner": false,
                "quotes": [
                    {
                        "rate": 4.08755862,
                        "fee": 2.99,
                        "receivedAmount": 396.53,
                        "dateCollected": "2023-01-24T07:43:58.547494Z",
                        "sourceCountry": "DE",
                        "targetCountry": "PE",
                        "markup": 3.11913698,
                        "deliveryEstimation": {
                            "duration": null,
                            "providerGivesEstimate": true
                        }
                    }
                ]
            },
            {
                "id": 7,
                "alias": "bbva",
                "name": "BBVA",
                "logo": "https://dq8dwmysp7hk1.cloudfront.net/logos/bbva.svg",
                "logos": {
                    "normal": {
                        "svgUrl": "https://dq8dwmysp7hk1.cloudfront.net/logos/bbva.svg",
                        "pngUrl": "https://dq8dwmysp7hk1.cloudfront.net/logos/bbva.png"
                    },
                    "inverse": {
                        "svgUrl": null,
                        "pngUrl": null
                    },
                    "white": {
                        "svgUrl": "https://dq8dwmysp7hk1.cloudfront.net/logos/bbva--white.svg",
                        "pngUrl": "https://dq8dwmysp7hk1.cloudfront.net/logos/bbva--white.png"
                    }
                },
                "type": "bank",
                "partner": false,
                "quotes": [
                    {
                        "rate": 4.01876057,
                        "fee": 45.0,
                        "receivedAmount": 221.03,
                        "dateCollected": "2023-01-24T07:50:09.863855Z",
                        "sourceCountry": "ES",
                        "targetCountry": null,
                        "markup": 4.74974711,
                        "deliveryEstimation": {
                            "duration": null,
                            "providerGivesEstimate": true
                        }
                    }
                ]
            },
            {
                "id": 39,
                "alias": "wise",
                "name": "Wise",
                "logo": "https://wise.com/public-resources/assets/logos/wise/brand_logo.svg",
                "logos": {
                    "normal": {
                        "svgUrl": "https://wise.com/public-resources/assets/logos/wise/brand_logo.svg",
                        "pngUrl": "https://wise.com/public-resources/assets/logos/wise/brand_logo.png"
                    },
                    "inverse": {
                        "svgUrl": "https://wise.com/public-resources/assets/logos/wise/brand_logo_inverse.svg",
                        "pngUrl": "https://wise.com/public-resources/assets/logos/wise/brand_logo_inverse.png"
                    },
                    "white": {
                        "svgUrl": "https://wise.com/public-resources/assets/logos/wise/brand_logo_white.svg",
                        "pngUrl": "https://wise.com/public-resources/assets/logos/wise/brand_logo_white.png"
                    }
                },
                "type": "moneyTransferProvider",
                "partner": false,
                "quotes": [
                    {
                        "rate": 4.21916,
                        "fee": 8.88,
                        "receivedAmount": 384.45,
                        "dateCollected": "2023-01-24T07:02:26.322736Z",
                        "sourceCountry": null,
                        "targetCountry": null,
                        "markup": 0.0,
                        "deliveryEstimation": {
                            "duration": null,
                            "providerGivesEstimate": true
                        }
                    }
                ]
            },
            {
                "id": 59,
                "alias": "ofx",
                "name": "OFX",
                "logo": "https://dq8dwmysp7hk1.cloudfront.net/logos/ofx.svg",
                "logos": {
                    "normal": {
                        "svgUrl": "https://dq8dwmysp7hk1.cloudfront.net/logos/ofx.svg",
                        "pngUrl": "https://dq8dwmysp7hk1.cloudfront.net/logos/ofx.png"
                    },
                    "inverse": {
                        "svgUrl": null,
                        "pngUrl": null
                    },
                    "white": {
                        "svgUrl": "https://dq8dwmysp7hk1.cloudfront.net/logos/ofx--white.svg",
                        "pngUrl": "https://dq8dwmysp7hk1.cloudfront.net/logos/ofx--white.png"
                    }
                },
                "type": "moneyTransferProvider",
                "partner": false,
                "quotes": [
                    {
                        "rate": 4.09729998,
                        "fee": 0.0,
                        "receivedAmount": 409.73,
                        "dateCollected": "2023-01-24T07:23:10.995293Z",
                        "sourceCountry": null,
                        "targetCountry": null,
                        "markup": 2.88825311,
                        "deliveryEstimation": {
                            "duration": null,
                            "providerGivesEstimate": true
                        }
                    }
                ]
            }
        ]
    },
    "PYG": {
        "sourceCurrency": "EUR",
        "targetCurrency": "PYG",
        "sourceCountry": null,
        "targetCountry": null,
        "providerCountry": null,
        "providerType": null,
        "sendAmount": 100.0,
        "providers": []
    },
    "SVC": {
        "sourceCurrency": "EUR",
        "targetCurrency": "SVC",
        "sourceCountry": null,
        "targetCountry": null,
        "providerCountry": null,
        "providerType": null,
        "sendAmount": 100.0,
        "providers": []
    },
    "UYU": {
        "sourceCurrency": "EUR",
        "targetCurrency": "UYU",
        "sourceCountry": null,
        "targetCountry": null,
        "providerCountry": null,
        "providerType": null,
        "sendAmount": 100.0,
        "providers": [
            {
                "id": 104,
                "alias": "remitly",
                "name": "Remitly",
                "logo": "https://dq8dwmysp7hk1.cloudfront.net/logos/remitly.svg",
                "logos": {
                    "normal": {
                        "svgUrl": "https://dq8dwmysp7hk1.cloudfront.net/logos/remitly.svg",
                        "pngUrl": "https://dq8dwmysp7hk1.cloudfront.net/logos/remitly.png"
                    },
                    "inverse": {
                        "svgUrl": null,
                        "pngUrl": null
                    },
                    "white": {
                        "svgUrl": "https://dq8dwmysp7hk1.cloudfront.net/logos/remitly--white.svg",
                        "pngUrl": "https://dq8dwmysp7hk1.cloudfront.net/logos/remitly--white.png"
                    }
                },
                "type": "moneyTransferProvider",
                "partner": false,
                "quotes": [
                    {
                        "rate": 41.63520255,
                        "fee": 3.49,
                        "receivedAmount": 4018.21,
                        "dateCollected": "2023-01-24T07:44:08.180046Z",
                        "sourceCountry": "DE",
                        "targetCountry": "UY",
                        "markup": 2.372036,
                        "deliveryEstimation": {
                            "duration": null,
                            "providerGivesEstimate": true
                        }
                    }
                ]
            },
            {
                "id": 39,
                "alias": "wise",
                "name": "Wise",
                "logo": "https://wise.com/public-resources/assets/logos/wise/brand_logo.svg",
                "logos": {
                    "normal": {
                        "svgUrl": "https://wise.com/public-resources/assets/logos/wise/brand_logo.svg",
                        "pngUrl": "https://wise.com/public-resources/assets/logos/wise/brand_logo.png"
                    },
                    "inverse": {
                        "svgUrl": "https://wise.com/public-resources/assets/logos/wise/brand_logo_inverse.svg",
                        "pngUrl": "https://wise.com/public-resources/assets/logos/wise/brand_logo_inverse.png"
                    },
                    "white": {
                        "svgUrl": "https://wise.com/public-resources/assets/logos/wise/brand_logo_white.svg",
                        "pngUrl": "https://wise.com/public-resources/assets/logos/wise/brand_logo_white.png"
                    }
                },
                "type": "moneyTransferProvider",
                "partner": false,
                "quotes": [
                    {
                        "rate": 42.6468,
                        "fee": 6.32,
                        "receivedAmount": 3995.15,
                        "dateCollected": "2023-01-24T08:01:16Z",
                        "sourceCountry": null,
                        "targetCountry": null,
                        "markup": 0.0,
                        "deliveryEstimation": {
                            "duration": {
                                "min": "PT147H58M43.775480153S",
                                "max": "PT147H58M43.775480153S"
                            },
                            "providerGivesEstimate": true
                        }
                    }
                ]
            }
        ]
    },
    "VEF": {
        "sourceCurrency": "EUR",
        "targetCurrency": "VEF",
        "sourceCountry": null,
        "targetCountry": null,
        "providerCountry": null,
        "providerType": null,
        "sendAmount": 100.0,
        "providers": []
    }
}